{
    "stats": {
        "duelsLost": 15.0,
        "penaltiesSaved": 0,
        "fiftyFifty": 0,
        "blockedShots": 3.0,
        "shotsOnTargetIncGoals": 1.0,
        "expectedGoalsOnTarget": 0.1971,
        "totalTackles": 5.0,
        "throughBalls": 0,
        "gamesPlayed": 7.0,
        "setPiecesGoals": 0,
        "successfulFiftyFifty": 0,
        "totalPasses": 123.0,
        "goals": 0,
        "offsides": 0,
        "awayGoals": 0,
        "oboxBlocked": 1.0,
        "substituteOn": 1.0,
        "index": 0,
        "penaltiesFaced": 0,
        "iboxTarget": 1.0,
        "aerialDuelsLost": 4.0,
        "goalsConcededOutsideBox": 1.0,
        "groundDuelsWon": 6.0,
        "successfulCornersIntoBox": 0,
        "penaltyGoalsConceded": 0,
        "expectedGoalsOnTargetConceded": 4.9605,
        "ownGoalScored": 0,
        "keyPassesAttemptAssists": 4.0,
        "successfulLaunches": 0,
        "totalFoulsWon": 0,
        "winningGoal": 0.0,
        "recoveries": 17.0,
        "appearances": 7.0,
        "rightFootGoals": 0,
        "crossesNotClaimed": 0,
        "leftFootGoals": 0,
        "unsuccessfulDribbles": 2.0,
        "redCards2ndYellow": 0,
        "unsuccessfulCrossesAndCorners": 16.0,
        "otherGoals": 0,
        "timesTackled": 5.0,
        "freekickTotal": 0,
        "gkSuccessfulDistribution": 0,
        "openPlayPasses": 123.0,
        "shotsOffTargetIncWoodwork": 4.0,
        "totalLossesOfPossession": 50.0,
        "tacklesWon": 2.0,
        "attemptsFromSetPieces": 0,
        "savesMadeParried": 0,
        "leftsidePasses": 40.0,
        "totalFoulsConceded": 1.0,
        "unsuccessfulCornersIntoBox": 0,
        "clearancesOffTheLine": 0,
        "successfulLongPasses": 4.0,
        "backwardPasses": 48.0,
        "touches": 201.0,
        "throwInsToOwnPlayer": 6.0,
        "hitWoodwork": 0,
        "goalsFromInsideBox": 0,
        "successfulPassesOwnHalf": 43.0,
        "savesMadeFromInsideBox": 0,
        "handballsConceded": 0,
        "unsuccessfulLongPasses": 3.0,
        "unsuccessfulPassesOwnHalf": 5.0,
        "secondGoalAssists": 0,
        "successfulCrossesOpenPlay": 4.0,
        "expectedAssists": 0.314,
        "totalRedCards": 0.0,
        "expectedGoalsFreekick": 0,
        "catches": 0,
        "overruns": 2.0,
        "savesMadeFromOutsideBox": 0,
        "totalShots": 5.0,
        "unsuccessfulShortPasses": 14.0,
        "goalAssists": 1.0,
        "successfulLayoffs": 8.0,
        "foulWonPenalty": 0,
        "setPieceGoals": 0,
        "starts": 6.0,
        "totalUnsuccessfulPassesExclCrossesAndCorners": 17.0,
        "unsuccessfulCrossesOpenPlay": 16.0,
        "goalKicks": 0,
        "savesMadeCaught": 0,
        "cornersTakenInclShortCorners": 0,
        "aerialDuels": 4.0,
        "cleanSheets": 2.0,
        "successfulCrossesAndCorners": 4.0,
        "timePlayed": 504.0,
        "unsuccessfulLayoffs": 0,
        "duelsWon": 6.0,
        "penaltiesConceded": 0,
        "putthroughBlockedDistribution": 9.0,
        "successfulShortPasses": 102.0,
        "savesFromPenalty": 0,
        "totalTouchesInOppositionBox": 15.0,
        "throwInsToOppositionPlayer": 0,
        "successfulOpenPlayPasses": 0,
        "punches": 0,
        "cornersTakenIncShortCorners": 0,
        "totalSuccessfulPassesExclCrossesAndCorners": 0,
        "totalClearances": 8.0,
        "goalsConceded": 2.0,
        "groundDuelsLost": 11.0,
        "rightsidePasses": 21.0,
        "savesMade": 0,
        "duels": 21.0,
        "putthroughBlockedDistributionWon": 4.0,
        "homeGoals": 0,
        "goalkeeperSmother": 0,
        "forwardPasses": 14.0,
        "penaltiesTaken": 0,
        "oboxTarget": 0,
        "drops": 0,
        "tacklesLost": 3.0,
        "lastPlayerTackle": 0,
        "successfulPassesOppositionHalf": 67.0,
        "goalsConcededInsideBox": 1.0,
        "headedGoals": 0,
        "iboxBlocked": 2.0,
        "groundDuels": 17.0,
        "aerialDuelsWon": 0,
        "straightRedCards": 0.0,
        "cornersWon": 3.0,
        "successfulDribbles": 1.0,
        "blocks": 0,
        "gkUnsuccessfulDistribution": 0,
        "interceptions": 0,
        "penaltyGoals": 0,
        "assistsIntentional": 0,
        "substituteOff": 5.0,
        "unsuccessfulLaunches": 1.0,
        "foulAttemptedTackle": 0,
        "expectedGoals": 0.8941,
        "goalsFromOutsideBox": 0,
        "yellowCards": 0.0
    },
    "player": {
        "currentTeam": {
            "name": "Sunderland",
            "id": "56",
            "shortName": "Sunderland"
        },
        "firstName": "Chemsdine",
        "lastName": "Talbi",
        "country": {
            "isoCode": "MA",
            "country": "Morocco",
            "demonym": "Moroccan"
        },
        "name": "Chemsdine Talbi",
        "id": "549912",
        "position": "Forward"
    }
}